rushclis/__init__.py
rushclis/command.py
rushclis/help.py
rushclis-0.1.2.dist-info/licenses/LICENSE.txt
scripts/build.py
scripts/install.py
rushclis-0.1.2.dist-info/METADATA
rushclis-0.1.2.dist-info/WHEEL
rushclis-0.1.2.dist-info/top_level.txt
rushclis-0.1.2.dist-info/RECORD
