Metadata-Version: 2.4
Name: rushclis
Version: 0.1.2
Summary: python cli
Author-email: ndrzy <dandan0019@outlook.com>
License: MIT
Project-URL: Homepage, https://github.com/meatdumplings0019/rushclis
Requires-Python: >=3.10
License-File: LICENSE.txt
Requires-Dist: colorama
Requires-Dist: rushlib
Dynamic: license-file
